{
  "id" : "VerifyExistenceOfSupplierCandidate",
  "name" : "VerifyExistenceOfSupplierCandidate",
  "type" : "form",
  "uuid" : "8eca6d1b-837e-4036-b115-85ef10922c79",
  "modelVersion" : "2.6",
  "lastUpdate" : 1749579887564,
  "description" : "Page generated with Bonita UI designer",
  "rows" : [
    [
      {
        "type" : "component",
        "dimension" : {
          "xs" : 12,
          "sm" : 12,
          "md" : 12,
          "lg" : 12
        },
        "propertyValues" : {
          "cssClasses" : {
            "type" : "constant",
            "value" : ""
          },
          "hidden" : {
            "type" : "constant",
            "value" : false
          },
          "allowHTML" : {
            "type" : "constant",
            "value" : false
          },
          "text" : {
            "type" : "interpolation",
            "value" : "Tem algum possível fornecedor em mente?"
          },
          "level" : {
            "type" : "constant",
            "value" : "Level 2"
          },
          "alignment" : {
            "type" : "constant",
            "value" : "center"
          }
        },
        "reference" : "01ad06db-71d7-4044-97b3-336ed038fb5b",
        "hasValidationError" : false,
        "id" : "pbTitle"
      }
    ],
    [
      {
        "type" : "component",
        "dimension" : {
          "xs" : 12,
          "sm" : 12,
          "md" : 12,
          "lg" : 12
        },
        "propertyValues" : {
          "cssClasses" : {
            "type" : "constant",
            "value" : ""
          },
          "hidden" : {
            "type" : "constant",
            "value" : false
          },
          "disabled" : {
            "type" : "constant",
            "value" : false
          },
          "required" : {
            "type" : "constant",
            "value" : true
          },
          "allowHTML" : {
            "type" : "constant",
            "value" : true
          },
          "labelHidden" : {
            "type" : "constant",
            "value" : true
          },
          "label" : {
            "type" : "interpolation",
            "value" : ""
          },
          "labelPosition" : {
            "type" : "constant",
            "value" : "top"
          },
          "labelWidth" : {
            "type" : "constant",
            "value" : 4
          },
          "inline" : {
            "type" : "constant",
            "value" : false
          },
          "availableValues" : {
            "type" : "expression",
            "value" : "[   { label: \"Sim\", value: true },   { label: \"Não\", value: false } ]"
          },
          "displayedKey" : {
            "type" : "constant",
            "value" : "label"
          },
          "returnedKey" : {
            "type" : "constant",
            "value" : "value"
          },
          "selectedValue" : {
            "type" : "variable",
            "value" : "selectedSupplier"
          }
        },
        "reference" : "dbad9497-a8ce-4f26-92c9-596fc6fc9f32",
        "hasValidationError" : false,
        "id" : "pbRadioButtons"
      }
    ],
    [
      {
        "type" : "component",
        "dimension" : {
          "xs" : 12,
          "sm" : 12,
          "md" : 12,
          "lg" : 12
        },
        "propertyValues" : {
          "cssClasses" : {
            "type" : "constant",
            "value" : ""
          },
          "hidden" : {
            "type" : "constant",
            "value" : false
          },
          "disabled" : {
            "type" : "constant",
            "value" : false
          },
          "allowHTML" : {
            "type" : "constant",
            "value" : false
          },
          "label" : {
            "type" : "interpolation",
            "value" : "Submeter"
          },
          "alignment" : {
            "type" : "constant",
            "value" : "left"
          },
          "buttonStyle" : {
            "type" : "constant",
            "value" : "primary"
          },
          "action" : {
            "type" : "constant",
            "value" : "Submit task"
          },
          "assign" : {
            "type" : "constant",
            "value" : false
          },
          "url" : {
            "type" : "interpolation"
          },
          "responseStatusCode" : {
            "type" : "variable"
          },
          "dataToSend" : {
            "type" : "expression",
            "value" : "{     \"selectedInput\": selectedSupplier }"
          },
          "dataFromSuccess" : {
            "type" : "variable",
            "value" : "checkboxSupplierCandidate"
          },
          "closeOnSuccess" : {
            "type" : "constant",
            "value" : false
          },
          "dataFromError" : {
            "type" : "variable"
          },
          "targetUrlOnSuccess" : {
            "type" : "interpolation"
          },
          "collectionToModify" : {
            "type" : "variable"
          },
          "modalId" : {
            "type" : "constant",
            "value" : ""
          },
          "collectionPosition" : {
            "type" : "constant",
            "value" : "Last"
          },
          "valueToAdd" : {
            "type" : "constant"
          },
          "removeItem" : {
            "type" : "variable"
          }
        },
        "reference" : "2bbd5cc9-aeff-448f-89cc-828ed68ad189",
        "hasValidationError" : false,
        "id" : "pbButton"
      }
    ]
  ],
  "variables" : {
    "selectedSupplier" : {
      "type" : "constant",
      "value" : [
        ""
      ],
      "exposed" : false
    }
  },
  "assets" : [
    {
      "id" : "e38a2dfa-5485-47ed-9a7b-c518658df764",
      "name" : "style.css",
      "type" : "css",
      "order" : 0,
      "external" : false
    },
    {
      "id" : "23dcb579-7065-4296-b0d5-61aebdaa35c1",
      "name" : "localization.json",
      "type" : "json",
      "order" : 0,
      "external" : false
    }
  ],
  "inactiveAssets" : [ ],
  "webResources" : [ ],
  "hasValidationError" : false
}